settransformer/__init__.py
tf_settransformer-0.3.1.dist-info/LICENSE
tf_settransformer-0.3.1.dist-info/METADATA
tf_settransformer-0.3.1.dist-info/WHEEL
tf_settransformer-0.3.1.dist-info/top_level.txt
tf_settransformer-0.3.1.dist-info/RECORD
