Metadata-Version: 2.1
Name: tf-settransformer
Version: 0.3.1
Summary: An unofficial implementation of the Set Transformer framework in Tensorflow/Keras based on the paper: Set Transformer: A Framework for Attention-based Permutation-Invariant Neural Networks
Author-email: David Ludwig <davidludwigii@gmail.com>
License: MIT License
Project-URL: Homepage, https://github.com/DLii-Research/tf-settransformer
Project-URL: Bug Tracker, https://github.com/DLii-Research/tf-settransformer/issues
Classifier: Programming Language :: Python :: 3
Classifier: License :: OSI Approved :: MIT License
Classifier: Operating System :: OS Independent
Requires-Python: >=3.6
License-File: LICENSE
